fpstreams/__init__.py
fpstreams/exceptions.py
fpstreams/functional.py
fpstreams/option.py
fpstreams/py.typed
fpstreams/result.py
fpstreams/core/__init__.py
fpstreams/core/async_ops.py
fpstreams/core/async_stream.py
fpstreams/core/collectors.py
fpstreams/core/common.py
fpstreams/core/ops.py
fpstreams/core/parallel.py
fpstreams/core/sequential.py
fpstreams/core/stream_interface.py
fpstreams-1.0.0.dist-info/METADATA
fpstreams-1.0.0.dist-info/WHEEL
fpstreams-1.0.0.dist-info/top_level.txt
fpstreams-1.0.0.dist-info/RECORD
