Metadata-Version: 2.4
Name: fpstreams
Version: 1.0.0
Summary: A functional programming library for Python mimicking Java Streams and JS Arrays.
Author-email: Steven Yang <stevenyang0316@gmail.com>
Project-URL: Homepage, https://github.com/steventimes/fpstreams
Project-URL: Bug Tracker, https://github.com/steventimes/fpstreams/issues
Project-URL: Documentation, https://github.com/steventimes/fpstreams/README.md
Classifier: Programming Language :: Python :: 3
Classifier: License :: OSI Approved :: MIT License
Classifier: Operating System :: OS Independent
Classifier: Typing :: Typed
Requires-Python: >=3.10
Provides-Extra: test
Requires-Dist: pytest; extra == "test"
Requires-Dist: pytest-asyncio; extra == "test"
Requires-Dist: aiofiles; extra == "test"
Provides-Extra: async
Requires-Dist: aiofiles; extra == "async"
Provides-Extra: data
Requires-Dist: numpy; extra == "data"
Requires-Dist: pandas; extra == "data"
Provides-Extra: all
Requires-Dist: pytest; extra == "all"
Requires-Dist: pytest-asyncio; extra == "all"
Requires-Dist: aiofiles; extra == "all"
Requires-Dist: numpy; extra == "all"
Requires-Dist: pandas; extra == "all"
Provides-Extra: keywords
Requires-Dist: functional; extra == "keywords"
Requires-Dist: streams; extra == "keywords"
Requires-Dist: java-streams; extra == "keywords"
Requires-Dist: monad; extra == "keywords"
Requires-Dist: pipeline; extra == "keywords"
Requires-Dist: data-science; extra == "keywords"
